custard/__init__.py
custard/core/__init__.py
custard/core/decode.py
custard/core/factory.py
custard/core/functools.py
custard/core/kerberos.py
custard/core/processor.py
custard/core/regular.py
custard/core/system.py
custard/core/useragent.py
custard/core/xml2dict.py
custard/core/xprint.py
custard/crypto/__init__.py
custard/crypto/crypto.py
custard/crypto/streambody.py
custard/curl/__init__.py
custard/curl/parse.py
custard/hitfilter/__init__.py
custard/hitfilter/hitfilter.py
custard/hitfilter/keywords
custard/kaptcha/__init__.py
custard/kaptcha/captcha.py
custard/kaptcha/font1.ttf
custard/kaptcha/font2.ttf
custard/kaptcha/font3.ttf
custard/kaptcha/font4.ttf
custard/limiter/README.md
custard/limiter/__init__.py
custard/limiter/depends.py
custard/limiter/enums.py
custard/limiter/examples/__init__.py
custard/limiter/examples/test_depends.py
custard/limiter/execres.py
custard/logstash/__init__.py
custard/logstash/cache.py
custard/logstash/constants.py
custard/logstash/database.py
custard/logstash/docs/config_logstash.md
custard/logstash/docs/usage.md
custard/logstash/examples/example1.py
custard/logstash/examples/example2.py
custard/logstash/examples/example3.py
custard/logstash/formatter.py
custard/logstash/handler.py
custard/logstash/memory_cache.py
custard/logstash/tests/__init__.py
custard/logstash/tests/database_test.py
custard/logstash/tests/formatter_test.py
custard/logstash/tests/ichunked_test.py
custard/logstash/tests/memory_cache_test.py
custard/logstash/transport.py
custard/logstash/utils.py
custard/logstash/worker.py
custard/mock/__init__.py
custard/mock/mini_racer.py
custard/mock/mock.min.js
custard/mock/mock.old.min.js
custard/pagination/__init__.py
custard/pagination/api.py
custard/pagination/async_sqlalchemy.py
custard/pagination/bases.py
custard/pagination/iterables.py
custard/pagination/limit_offset.py
custard/pagination/pagination.py
custard/pagination/paginator.py
custard/pagination/sync_sqlalchemy.py
custard/swagger/__init__.py
custard-1.1.7.dist-info/METADATA
custard-1.1.7.dist-info/WHEEL
custard-1.1.7.dist-info/RECORD
