Metadata-Version: 2.1
Name: custard
Version: 1.1.7
Summary: custard easy to learn, fast to code, ready for production
Home-page: https://github.com/kamalyes/custard
License: MIT
Author: Kamalyes
Author-email: mryu168@163.com
Requires-Python: >=3.9,<4.0
Classifier: Development Status :: 4 - Beta
Classifier: Intended Audience :: Developers
Classifier: Intended Audience :: System Administrators
Classifier: License :: OSI Approved :: MIT License
Classifier: Operating System :: OS Independent
Classifier: Programming Language :: Python
Classifier: Programming Language :: Python :: 3
Classifier: Programming Language :: Python :: 3.9
Classifier: Programming Language :: Python :: 3.10
Classifier: Programming Language :: Python :: 3.11
Classifier: Programming Language :: Python :: 3.8
Classifier: Topic :: Software Development :: Libraries :: Python Modules
Classifier: Typing :: Typed
Provides-Extra: all
Requires-Dist: Faker (>=13.6.0,<18.11.0) ; extra == "all"
Requires-Dist: Jinja2 (>=3.1.2,<4.0.0)
Requires-Dist: PyYAML (>=6.0,<7.0) ; extra == "all"
Requires-Dist: SQLAlchemy (>=1.3.20,<2.0.17) ; extra == "all"
Requires-Dist: aioredis (>=2.0.1,<3.0.0) ; extra == "all"
Requires-Dist: asgi-lifespan (>=2.1.0,<3.0.0)
Requires-Dist: certifi (<=2023.5.7) ; extra == "all"
Requires-Dist: contextvars (>=2.4,<3.0) ; extra == "all"
Requires-Dist: crypto (>=1.4.1,<2.0.0) ; extra == "all"
Requires-Dist: dicttoxml (>=1.7.4,<2.0.0) ; extra == "all"
Requires-Dist: fastapi (>=0.78.0,<0.95.2) ; extra == "all"
Requires-Dist: httpx (>=0.24.0,<0.25.0)
Requires-Dist: kafka (>=1.3.5,<2.0.0) ; extra == "all"
Requires-Dist: limits (>=3.5.0)
Requires-Dist: lxml (>=4.9.0,<5.0.0) ; extra == "all"
Requires-Dist: mkdocs (>=1.4.1,<2.0.0) ; extra == "all"
Requires-Dist: mkdocs-material (>=9.1.8,<10.0.0)
Requires-Dist: mypy (>=1.2.0,<2.0.0)
Requires-Dist: pillow (>=9.5.0,<10.0.0)
Requires-Dist: psycopg2-binary (>=2.9.5,<3.0.0)
Requires-Dist: py_mini_racer (>=0.6.0,<0.7.0)
Requires-Dist: pydantic (>=1.9.1) ; extra == "all"
Requires-Dist: pyjwt (>=2.4.0,<3.0.0) ; extra == "all"
Requires-Dist: pylogbeat (>=2.0.0)
Requires-Dist: pypinyin (>=0.39.1,<0.50.0) ; extra == "all"
Requires-Dist: redis (>=3.5.3,<5.0.0) ; extra == "all"
Requires-Dist: requests (>=2.29.0,<3.0.0) ; extra == "all"
Requires-Dist: ruff (>=0.0.263,<0.0.273)
Requires-Dist: simplejson (>=3.17.6)
Requires-Dist: six (>=1.16.0,<2.0.0) ; extra == "all"
Requires-Dist: starlette (>=0.19.1,<0.27.0) ; extra == "all"
Requires-Dist: types-PyYAML (>=6.0.12.9,<7.0.0.0)
Requires-Dist: types-python-dateutil (>=2.8.19.12,<3.0.0.0)
Requires-Dist: types-requests (>=2.29.0.0,<3.0.0.0)
Requires-Dist: types-simplejson (>=3.19.0.0,<4.0.0.0)
Requires-Dist: types-urllib3 (>=1.26.25.11,<2.0.0.0)
Requires-Dist: urllib3 (>=1.26.12,<3.0.0) ; extra == "all"
Requires-Dist: uvicorn (>=0.17.6,<0.23.0) ; extra == "all"
Requires-Dist: w3lib (>=2.1.1,<3.0.0) ; extra == "all"
Project-URL: Repository, https://github.com/kamalyes/custard
